README.md
__init__.py
setup.cfg
setup.py
distortiongenerator/__init__.py
distortiongenerator.egg-info/PKG-INFO
distortiongenerator.egg-info/SOURCES.txt
distortiongenerator.egg-info/dependency_links.txt
distortiongenerator.egg-info/requires.txt
distortiongenerator.egg-info/top_level.txt
distortiongenerator/__pycache__/__init__.cpython-36.pyc
distortiongenerator/__pycache__/__init__.cpython-37.pyc
distortiongenerator/distortion/__init__.py
distortiongenerator/distortion/blur.py
distortiongenerator/distortion/composition.py
distortiongenerator/distortion/compression.py
distortiongenerator/distortion/enhancement.py
distortiongenerator/distortion/noise.py
distortiongenerator/distortion/__pycache__/__init__.cpython-36.pyc
distortiongenerator/distortion/__pycache__/__init__.cpython-37.pyc
distortiongenerator/distortion/__pycache__/blur.cpython-36.pyc
distortiongenerator/distortion/__pycache__/blur.cpython-37.pyc
distortiongenerator/distortion/__pycache__/composition.cpython-36.pyc
distortiongenerator/distortion/__pycache__/composition.cpython-37.pyc
distortiongenerator/distortion/__pycache__/compression.cpython-36.pyc
distortiongenerator/distortion/__pycache__/compression.cpython-37.pyc
distortiongenerator/distortion/__pycache__/enhancement.cpython-36.pyc
distortiongenerator/distortion/__pycache__/enhancement.cpython-37.pyc
distortiongenerator/distortion/__pycache__/noise.cpython-36.pyc
distortiongenerator/distortion/__pycache__/noise.cpython-37.pyc
resources/logo-epfl.png
resources/mmspglogo.png