Metadata-Version: 2.1
Name: distortiongenerator
Version: 0.2
Summary: UNKNOWN
Home-page: https://github.com/louzi233/DistortionGenerator
License: MIT
Platform: UNKNOWN
